qcpy/__init__.py
qcpy/qubit.py
qcpy/circuitdrawing/__init__.py
qcpy/circuitdrawing/circuitdrawing.py
qcpy/circuitdrawing/gateformatting.py
qcpy/circuitdrawing/quantumgatedraw.py
qcpy/core/__init__.py
qcpy/core/quantumcircuit.py
qcpy/core/cqc/__init__.py
qcpy/core/cqc/quantumcircuit.py
qcpy/core/tools/__init__.py
qcpy/core/tools/amplitude.py
qcpy/core/tools/measure.py
qcpy/core/tools/phaseangle.py
qcpy/core/tools/probabilities.py
qcpy/quantumgate/__init__.py
qcpy/quantumgate/multiqubit.py
qcpy/quantumgate/singlequbit.py
qcpy/visualizer/__init__.py
qcpy/visualizer/bloch.py
qcpy/visualizer/probability.py
qcpy/visualizer/qsphere.py
qcpy/visualizer/statevector.py
qcpy/visualizer/tools/__init__.py
qcpy/visualizer/tools/graph.py
qcpy/visualizer/tools/sphere.py
test/__init__.py
test/quantumcircuit/__init__.py
test/quantumcircuit/test_qc_01.py
test/quantumcircuit/test_qc_02.py
test/quantumcircuit/test_qc_03.py
test/quantumcircuit/test_qc_04.py
test/quantumcircuit/test_qc_05.py
test/quantumcircuit/test_qc_06.py
test/quantumcircuit/test_qc_07.py
test/quantumcircuit/test_qc_08.py
test/quantumcircuit/test_qc_09.py
test/quantumcircuit/test_qc_10.py
test/quantumcircuit/test_qc_11.py
test/quantumcircuit/test_qc_12.py
test/quantumcircuit/test_qc_13.py
test/quantumcircuit/test_qc_14.py
test/quantumcircuit/test_qc_15.py
test/quantumcircuit/test_qc_16.py
test/quantumcircuit/test_qc_17.py
test/quantumcircuit/test_qc_18.py
test/quantumcircuit/test_qc_19.py
test/quantumcircuit/test_qc_20.py
test/quantumgate/__init__.py
test/quantumgate/test_qg_01.py
test/quantumgate/test_qg_02.py
test/quantumgate/test_qg_03.py
test/quantumgate/test_qg_04.py
test/quantumgate/test_qg_05.py
test/quantumgate/test_qg_06.py
test/quantumgate/test_qg_07.py
test/quantumgate/test_qg_08.py
test/quantumgate/test_qg_09.py
test/quantumgate/test_qg_10.py
test/quantumgate/test_qg_11.py
test/quantumgate/test_qg_12.py
test/quantumgate/test_qg_13.py
test/quantumgate/test_qg_14.py
test/quantumgate/test_qg_15.py
qcpython-1.1.1.dist-info/LICENSE.txt
qcpython-1.1.1.dist-info/METADATA
qcpython-1.1.1.dist-info/WHEEL
qcpython-1.1.1.dist-info/top_level.txt
qcpython-1.1.1.dist-info/RECORD
