Metadata-Version: 2.1
Name: qcpython
Version: 1.1.1
Summary: QCpy is an open source python library and collaborative project for flexible simulations and visualizations of quantum circuits. Designed by college students with students in mind, this library contains a powerful set of tools to teach computer scientists about the emerging discipline of quantum computing.
Home-page: https://github.com/QCpython/QCpy
Author: Brennan Freeze, Paris Osuch, Aundre Barras, Soren Richenberg, Suzanne Rivoire
Author-email: freezebrennan@gmail.com, osuch@sonoma.edu, barras@sonoma.edu, richenbe@sonoma.edu, rivoire@sonoma.edu
Classifier: Programming Language :: Python :: 3
Classifier: License :: OSI Approved :: MIT License
Classifier: Operating System :: OS Independent
Requires-Python: >=3.8
License-File: LICENSE.txt
Requires-Dist: matplotlib (==3.7.2)
Requires-Dist: numpy (==1.25.1)
Requires-Dist: setuptools (==65.5.0)
Requires-Dist: scipy (==1.11.2)
Requires-Dist: pytest (==7.4.2)
